{
	"components": {
		"examples": {},
		"headers": {},
		"parameters": {},
		"requestBodies": {},
		"responses": {},
		"schemas": {
			"Article": {
				"properties": {
					"title": {
						"type": "string"
					},
					"body": {
						"type": "string"
					},
					"published": {
						"type": "boolean"
					},
					"year": {
						"type": "number",
						"format": "double"
					},
					"time_published": {
						"type": "string"
					},
					"picture": {
						"type": "string"
					},
					"id": {
						"type": "number",
						"format": "double"
					},
					"author": {
						"type": "number",
						"format": "double"
					},
					"resource": {
						"type": "string"
					}
				},
				"required": [
					"title",
					"body",
					"published",
					"year",
					"time_published",
					"picture",
					"id",
					"author",
					"resource"
				],
				"type": "object",
				"additionalProperties": false
			},
			"DirContent": {
				"properties": {
					"id": {
						"type": "string"
					},
					"files": {
						"items": {
							"type": "string"
						},
						"type": "array"
					},
					"dirs": {
						"items": {
							"type": "string"
						},
						"type": "array"
					}
				},
				"required": [
					"id",
					"files",
					"dirs"
				],
				"type": "object",
				"additionalProperties": false
			},
			"ArticlesResponse": {
				"properties": {
					"articles": {
						"items": {
							"$ref": "#/components/schemas/Article"
						},
						"type": "array"
					},
					"contents": {
						"items": {
							"$ref": "#/components/schemas/DirContent"
						},
						"type": "array"
					},
					"meta": {
						"properties": {
							"total": {
								"type": "number",
								"format": "double"
							}
						},
						"required": [
							"total"
						],
						"type": "object"
					}
				},
				"required": [
					"articles",
					"contents",
					"meta"
				],
				"type": "object",
				"additionalProperties": false
			},
			"ArticleCreation": {
				"properties": {
					"title": {
						"type": "string"
					},
					"body": {
						"type": "string"
					},
					"published": {
						"type": "boolean"
					},
					"year": {
						"type": "number",
						"format": "double"
					},
					"time_published": {
						"type": "string"
					},
					"picture": {
						"type": "string"
					}
				},
				"required": [
					"title",
					"body",
					"published",
					"year",
					"time_published",
					"picture"
				],
				"type": "object",
				"additionalProperties": false
			},
			"ArticleCreationRequest": {
				"properties": {
					"article": {
						"$ref": "#/components/schemas/ArticleCreation"
					}
				},
				"required": [
					"article"
				],
				"type": "object",
				"additionalProperties": false
			},
			"ArticleResponse": {
				"properties": {
					"article": {
						"$ref": "#/components/schemas/Article"
					},
					"contents": {
						"items": {
							"$ref": "#/components/schemas/DirContent"
						},
						"type": "array"
					}
				},
				"required": [
					"article",
					"contents"
				],
				"type": "object",
				"additionalProperties": false
			},
			"EmptyDict": {
				"properties": {},
				"type": "object",
				"additionalProperties": false
			},
			"Category": {
				"properties": {
					"id": {
						"type": "string"
					},
					"answer": {
						"type": "string"
					},
					"ftype": {
						"type": "string",
						"enum": [
							"stars",
							"line",
							"text_large"
						]
					},
					"text": {
						"type": "string"
					}
				},
				"required": [
					"id",
					"answer",
					"ftype",
					"text"
				],
				"type": "object",
				"additionalProperties": false
			},
			"FeedbackCreation": {
				"properties": {
					"categories": {
						"items": {
							"$ref": "#/components/schemas/Category"
						},
						"type": "array"
					},
					"taskId": {
						"type": "number",
						"format": "double"
					}
				},
				"required": [
					"categories",
					"taskId"
				],
				"type": "object",
				"additionalProperties": false
			},
			"FeedbackCreationRequest": {
				"properties": {
					"feedback": {
						"$ref": "#/components/schemas/FeedbackCreation"
					}
				},
				"required": [
					"feedback"
				],
				"type": "object",
				"additionalProperties": false
			},
			"Feedback": {
				"properties": {
					"categories": {
						"items": {
							"$ref": "#/components/schemas/Category"
						},
						"type": "array"
					},
					"taskId": {
						"type": "number",
						"format": "double"
					},
					"id": {
						"type": "number",
						"format": "double"
					},
					"userId": {
						"type": "number",
						"format": "double"
					},
					"lastUpdated": {
						"type": "string"
					},
					"filled": {
						"type": "boolean",
						"enum": [
							"true"
						],
						"nullable": false
					}
				},
				"required": [
					"categories",
					"taskId",
					"id",
					"userId",
					"lastUpdated",
					"filled"
				],
				"type": "object",
				"additionalProperties": false
			},
			"FeedbackResponse": {
				"properties": {
					"feedback": {
						"$ref": "#/components/schemas/Feedback"
					}
				},
				"required": [
					"feedback"
				],
				"type": "object",
				"additionalProperties": false
			},
			"FeedbackUpdate": {
				"properties": {
					"categories": {
						"items": {
							"$ref": "#/components/schemas/Category"
						},
						"type": "array"
					}
				},
				"required": [
					"categories"
				],
				"type": "object",
				"additionalProperties": false
			},
			"FeedbackUpdateRequest": {
				"properties": {
					"feedback": {
						"$ref": "#/components/schemas/FeedbackUpdate"
					}
				},
				"required": [
					"feedback"
				],
				"type": "object",
				"additionalProperties": false
			},
			"Year": {
				"properties": {
					"id": {
						"type": "number",
						"format": "double"
					},
					"year": {
						"type": "string"
					},
					"sealed": {
						"type": "boolean"
					},
					"point_pad": {
						"type": "number",
						"format": "double"
					},
					"active_orgs": {
						"items": {
							"type": "number",
							"format": "double"
						},
						"type": "array"
					},
					"sum_points": {
						"type": "number",
						"format": "double"
					},
					"tasks_cnt": {
						"type": "number",
						"format": "double"
					}
				},
				"required": [
					"id",
					"year",
					"sealed",
					"point_pad",
					"sum_points",
					"tasks_cnt"
				],
				"type": "object",
				"additionalProperties": false
			},
			"Years": {
				"properties": {
					"years": {
						"items": {
							"$ref": "#/components/schemas/Year"
						},
						"type": "array"
					}
				},
				"required": [
					"years"
				],
				"type": "object",
				"additionalProperties": false
			},
			"YearResponse": {
				"properties": {
					"year": {
						"$ref": "#/components/schemas/Year"
					}
				},
				"required": [
					"year"
				],
				"type": "object",
				"additionalProperties": false
			},
			"YearBase": {
				"properties": {
					"id": {
						"type": "number",
						"format": "double"
					},
					"year": {
						"type": "string"
					},
					"sealed": {
						"type": "boolean"
					},
					"point_pad": {
						"type": "number",
						"format": "double"
					},
					"active_orgs": {
						"items": {
							"type": "number",
							"format": "double"
						},
						"type": "array"
					}
				},
				"required": [
					"id",
					"year",
					"sealed",
					"point_pad"
				],
				"type": "object",
				"additionalProperties": false
			},
			"YearCreationRequest": {
				"properties": {
					"year": {
						"$ref": "#/components/schemas/YearBase"
					}
				},
				"required": [
					"year"
				],
				"type": "object",
				"additionalProperties": false
			},
			"YearUpdate": {
				"properties": {
					"id": {
						"type": "number",
						"format": "double"
					},
					"year": {
						"type": "string"
					},
					"sealed": {
						"type": "boolean"
					},
					"point_pad": {
						"type": "number",
						"format": "double"
					},
					"active_orgs": {
						"items": {
							"type": "number",
							"format": "double"
						},
						"type": "array"
					}
				},
				"required": [
					"id",
					"year",
					"sealed",
					"point_pad",
					"active_orgs"
				],
				"type": "object",
				"additionalProperties": false
			},
			"YearUpdateRequest": {
				"properties": {
					"year": {
						"$ref": "#/components/schemas/YearUpdate"
					}
				},
				"required": [
					"year"
				],
				"type": "object",
				"additionalProperties": false
			}
		},
		"securitySchemes": {
			"ksi": {
				"type": "oauth2",
				"flows": {
					"implicit": {
						"authorizationUrl": "https://ksi.fi.muni.cz/login/",
						"scopes": {}
					}
				}
			}
		}
	},
	"info": {
		"title": "web-backend-swagger",
		"version": "1.0.0",
		"license": {
			"name": "MIT"
		},
		"contact": {
			"name": "KSI"
		}
	},
	"openapi": "3.0.0",
	"paths": {
		"/articles": {
			"get": {
				"operationId": "YearsGetAll",
				"responses": {
					"200": {
						"description": "Ok",
						"content": {
							"application/json": {
								"schema": {
									"$ref": "#/components/schemas/ArticlesResponse"
								}
							}
						}
					}
				},
				"security": [
					{
						"ksi": []
					}
				],
				"parameters": [
					{
						"in": "query",
						"name": "_limit",
						"required": false,
						"schema": {
							"format": "double",
							"type": "number"
						}
					},
					{
						"in": "query",
						"name": "_start",
						"required": false,
						"schema": {
							"format": "double",
							"type": "number"
						}
					},
					{
						"in": "header",
						"name": "year",
						"required": false,
						"schema": {
							"format": "double",
							"type": "number"
						}
					}
				]
			},
			"post": {
				"operationId": "YearsCreateNew",
				"responses": {
					"200": {
						"description": "Ok",
						"content": {
							"application/json": {
								"schema": {
									"$ref": "#/components/schemas/ArticleCreationRequest"
								}
							}
						}
					}
				},
				"security": [
					{
						"ksi": []
					}
				],
				"parameters": [],
				"requestBody": {
					"required": true,
					"content": {
						"application/json": {
							"schema": {
								"$ref": "#/components/schemas/ArticleCreationRequest"
							}
						}
					}
				}
			}
		},
		"/articles/{articleId}": {
			"get": {
				"operationId": "YearsGetSingle",
				"responses": {
					"200": {
						"description": "Ok",
						"content": {
							"application/json": {
								"schema": {
									"$ref": "#/components/schemas/ArticleResponse"
								}
							}
						}
					}
				},
				"security": [
					{
						"ksi": []
					}
				],
				"parameters": [
					{
						"in": "path",
						"name": "articleId",
						"required": true,
						"schema": {
							"format": "double",
							"type": "number"
						}
					}
				]
			},
			"put": {
				"operationId": "YearsEditSingle",
				"responses": {
					"200": {
						"description": "Ok",
						"content": {
							"application/json": {
								"schema": {
									"$ref": "#/components/schemas/ArticleResponse"
								}
							}
						}
					}
				},
				"security": [
					{
						"ksi": []
					}
				],
				"parameters": [
					{
						"in": "path",
						"name": "articleId",
						"required": true,
						"schema": {
							"format": "double",
							"type": "number"
						}
					}
				],
				"requestBody": {
					"required": true,
					"content": {
						"application/json": {
							"schema": {
								"$ref": "#/components/schemas/ArticleCreationRequest"
							}
						}
					}
				}
			},
			"delete": {
				"operationId": "YearsDeleteSingle",
				"responses": {
					"200": {
						"description": "Ok",
						"content": {
							"application/json": {
								"schema": {
									"$ref": "#/components/schemas/EmptyDict"
								}
							}
						}
					}
				},
				"security": [
					{
						"ksi": []
					}
				],
				"parameters": [
					{
						"in": "path",
						"name": "articleId",
						"required": true,
						"schema": {
							"format": "double",
							"type": "number"
						}
					}
				]
			}
		},
		"/feedbacks": {
			"post": {
				"operationId": "FeedbackCreateNew",
				"responses": {
					"200": {
						"description": "Ok",
						"content": {
							"application/json": {
								"schema": {
									"$ref": "#/components/schemas/FeedbackCreationRequest"
								}
							}
						}
					}
				},
				"security": [
					{
						"ksi": []
					}
				],
				"parameters": [],
				"requestBody": {
					"required": true,
					"content": {
						"application/json": {
							"schema": {
								"$ref": "#/components/schemas/FeedbackCreationRequest"
							}
						}
					}
				}
			}
		},
		"/feedbacks/{feedbackId}": {
			"get": {
				"operationId": "FeedbackGetSingle",
				"responses": {
					"200": {
						"description": "Ok",
						"content": {
							"application/json": {
								"schema": {
									"$ref": "#/components/schemas/FeedbackResponse"
								}
							}
						}
					}
				},
				"security": [
					{
						"ksi": []
					}
				],
				"parameters": [
					{
						"in": "path",
						"name": "feedbackId",
						"required": true,
						"schema": {
							"format": "double",
							"type": "number"
						}
					}
				]
			},
			"put": {
				"operationId": "FeedbackEditSingle",
				"responses": {
					"200": {
						"description": "Ok",
						"content": {
							"application/json": {
								"schema": {
									"$ref": "#/components/schemas/FeedbackResponse"
								}
							}
						}
					}
				},
				"security": [
					{
						"ksi": []
					}
				],
				"parameters": [
					{
						"in": "path",
						"name": "feedbackId",
						"required": true,
						"schema": {
							"format": "double",
							"type": "number"
						}
					}
				],
				"requestBody": {
					"required": true,
					"content": {
						"application/json": {
							"schema": {
								"$ref": "#/components/schemas/FeedbackUpdateRequest"
							}
						}
					}
				}
			},
			"delete": {
				"operationId": "FeedbackDeleteSingle",
				"responses": {
					"200": {
						"description": "Ok",
						"content": {
							"application/json": {
								"schema": {
									"$ref": "#/components/schemas/EmptyDict"
								}
							}
						}
					}
				},
				"security": [
					{
						"ksi": []
					}
				],
				"parameters": [
					{
						"in": "path",
						"name": "feedbackId",
						"required": true,
						"schema": {
							"format": "double",
							"type": "number"
						}
					}
				]
			}
		},
		"/years": {
			"get": {
				"operationId": "YearsGetAll",
				"responses": {
					"200": {
						"description": "Ok",
						"content": {
							"application/json": {
								"schema": {
									"$ref": "#/components/schemas/Years"
								}
							}
						}
					}
				},
				"security": [],
				"parameters": []
			},
			"post": {
				"operationId": "YearsCreateNew",
				"responses": {
					"200": {
						"description": "Ok",
						"content": {
							"application/json": {
								"schema": {
									"$ref": "#/components/schemas/YearResponse"
								}
							}
						}
					}
				},
				"security": [
					{
						"ksi": []
					}
				],
				"parameters": [],
				"requestBody": {
					"required": true,
					"content": {
						"application/json": {
							"schema": {
								"$ref": "#/components/schemas/YearCreationRequest"
							}
						}
					}
				}
			}
		},
		"/years/{yearId}": {
			"get": {
				"operationId": "YearsGetSingle",
				"responses": {
					"200": {
						"description": "Ok",
						"content": {
							"application/json": {
								"schema": {
									"$ref": "#/components/schemas/YearResponse"
								}
							}
						}
					}
				},
				"security": [],
				"parameters": [
					{
						"in": "path",
						"name": "yearId",
						"required": true,
						"schema": {
							"format": "double",
							"type": "number"
						}
					}
				]
			},
			"put": {
				"operationId": "YearsUpdateSingle",
				"responses": {
					"200": {
						"description": "Ok",
						"content": {
							"application/json": {
								"schema": {
									"$ref": "#/components/schemas/YearResponse"
								}
							}
						}
					}
				},
				"security": [
					{
						"ksi": []
					}
				],
				"parameters": [
					{
						"in": "path",
						"name": "yearId",
						"required": true,
						"schema": {
							"format": "double",
							"type": "number"
						}
					}
				],
				"requestBody": {
					"required": true,
					"content": {
						"application/json": {
							"schema": {
								"$ref": "#/components/schemas/YearUpdateRequest"
							}
						}
					}
				}
			},
			"delete": {
				"operationId": "YearsDeleteSingle",
				"responses": {
					"200": {
						"description": "Ok",
						"content": {
							"application/json": {
								"schema": {
									"$ref": "#/components/schemas/EmptyDict"
								}
							}
						}
					}
				},
				"security": [
					{
						"ksi": []
					}
				],
				"parameters": [
					{
						"in": "path",
						"name": "yearId",
						"required": true,
						"schema": {
							"format": "double",
							"type": "number"
						}
					}
				]
			}
		}
	},
	"servers": [
		{
			"url": "/"
		}
	]
}